create_dump/__init__.py
create_dump/archiver.py
create_dump/banner.py
create_dump/caching.py
create_dump/cleanup.py
create_dump/core.py
create_dump/database.py
create_dump/helpers.py
create_dump/logging.py
create_dump/metrics.py
create_dump/notifications.py
create_dump/orchestrator.py
create_dump/path_utils.py
create_dump/processor.py
create_dump/single.py
create_dump/system.py
create_dump/transaction.py
create_dump/watch.py
create_dump/archive/__init__.py
create_dump/archive/core.py
create_dump/archive/finder.py
create_dump/archive/packager.py
create_dump/archive/pruner.py
create_dump/cli/__init__.py
create_dump/cli/batch.py
create_dump/cli/main.py
create_dump/cli/rollback.py
create_dump/cli/single.py
create_dump/collector/__init__.py
create_dump/collector/base.py
create_dump/collector/git_diff.py
create_dump/collector/git_ls.py
create_dump/collector/walk.py
create_dump/rollback/__init__.py
create_dump/rollback/engine.py
create_dump/rollback/parser.py
create_dump/scanning/__init__.py
create_dump/scanning/secret.py
create_dump/scanning/todo.py
create_dump/workflow/__init__.py
create_dump/workflow/single.py
create_dump/writing/__init__.py
create_dump/writing/checksum.py
create_dump/writing/json.py
create_dump/writing/markdown.py
create_dump-15.0.1.dist-info/METADATA
create_dump-15.0.1.dist-info/WHEEL
create_dump-15.0.1.dist-info/entry_points.txt
create_dump-15.0.1.dist-info/RECORD
