Metadata-Version: 2.4
Name: create-dump
Version: 15.0.1
Summary: Enterprise-grade code dump utility for monorepos
Project-URL: Homepage, https://pypi.org/project/create-dump/
Project-URL: Source, https://github.com/dhruv13x/create-dump
Project-URL: Issues, https://github.com/dhruv13x/create-dump/issues
Author-email: dhruv13x <dhruv13x@gmail.com>
License: MIT © dhruv13x
Classifier: License :: OSI Approved :: MIT License
Classifier: Programming Language :: Python :: 3
Classifier: Topic :: Software Development :: Documentation
Requires-Python: >=3.11
Requires-Dist: aiofiles>=23.0.0
Requires-Dist: anyio>=4.0.0
Requires-Dist: detect-secrets>=1.5.0
Requires-Dist: httpx>=0.25.0
Requires-Dist: pathspec>=0.12.0
Requires-Dist: prometheus-client>=0.20.0
Requires-Dist: pydantic>=2.0.0
Requires-Dist: rich>=13.0.0
Requires-Dist: structlog>=24.0.0
Requires-Dist: tenacity>=8.2.0
Requires-Dist: toml>=0.10.0
Requires-Dist: typer>=0.12.0
Requires-Dist: watchdog>=4.0.0
Provides-Extra: dev
Requires-Dist: black>=24.3.0; extra == 'dev'
Requires-Dist: mypy>=1.11.0; extra == 'dev'
Requires-Dist: pyfakefs>=5.0.0; extra == 'dev'
Requires-Dist: pytest-asyncio>=0.23.0; extra == 'dev'
Requires-Dist: pytest-cov>=5.0.0; extra == 'dev'
Requires-Dist: pytest-json-report>=1.5.0; extra == 'dev'
Requires-Dist: pytest-mock>=3.10.0; extra == 'dev'
Requires-Dist: pytest-timeout>=2.2.0; extra == 'dev'
Requires-Dist: pytest>=8.0.0; extra == 'dev'
Requires-Dist: pyyaml>=6.0; extra == 'dev'
Requires-Dist: ruff>=0.6.0; extra == 'dev'
Requires-Dist: types-pyyaml>=6.0; extra == 'dev'
